mypackage/__init__.py
mypackage/main.py
rss_reader_by_KisKass-2.1.dist-info/METADATA
rss_reader_by_KisKass-2.1.dist-info/WHEEL
rss_reader_by_KisKass-2.1.dist-info/entry_points.txt
rss_reader_by_KisKass-2.1.dist-info/top_level.txt
rss_reader_by_KisKass-2.1.dist-info/RECORD
