Metadata-Version: 2.1
Name: rss-reader-by-KisKass
Version: 2.1
Summary: "rss reader as my final task of practice"
Home-page: UNKNOWN
Author: KisKass
Author-email: 4231267@gmail.com
License: UNKNOWN
Platform: UNKNOWN
Classifier: Programming Language :: Python :: 3
Classifier: License :: OSI Approved :: MIT License
Classifier: Operating System :: OS Independent
Requires-Python: >=3.6
Requires-Dist: beautifulsoup4 (==4.9.3)
Requires-Dist: lxml (==4.6.3)
Requires-Dist: pip (==21.1.3)
Requires-Dist: setuptools (==56.0.0)
